knockssh/__init__.py
knockssh/command_executor.py
knockssh/config_loader.py
knockssh/config_saver.py
knockssh/logger_singleton.py
knockssh/main.py
knockssh-0.1.0.dist-info/licenses/LICENSE
knockssh-0.1.0.dist-info/METADATA
knockssh-0.1.0.dist-info/WHEEL
knockssh-0.1.0.dist-info/entry_points.txt
knockssh-0.1.0.dist-info/top_level.txt
knockssh-0.1.0.dist-info/RECORD
