Metadata-Version: 2.4
Name: knockssh
Version: 0.1.0
Summary: knockssh automates knock-and-ssh for a more convenient workflow
Author-email: Andreas Glashauser <ag@andreasglashauser.com>
License-Expression: MIT
Project-URL: Source, https://git.andreasglashauser.com/?p=knockssh.git
Classifier: Development Status :: 5 - Production/Stable
Classifier: Intended Audience :: Developers
Classifier: Programming Language :: Python :: 3
Requires-Python: >=3.6
License-File: LICENSE
Dynamic: license-file
